bcdc2bcdc/CKAN.py
bcdc2bcdc/CKANData.py
bcdc2bcdc/CKANScheming.py
bcdc2bcdc/CKANTransform.py
bcdc2bcdc/CKANUpdate.py
bcdc2bcdc/CacheFiles.py
bcdc2bcdc/CustomTransformers.py
bcdc2bcdc/DataCache.py
bcdc2bcdc/Diff.py
bcdc2bcdc/__init__.py
bcdc2bcdc/constants.py
bcdc2bcdc-0.0.10.data/scripts/runBCDC2BCDC.py
bcdc2bcdc_config/logger.config
bcdc2bcdc_config/transformationConfig_NewDataModel.json
bcdc2bcdc_config/transformationConfig_prod2cat.json
bcdc2bcdc_config/transformationConfig_prod2cati.json
tests/__init__.py
tests/conftest.py
tests/test_CKAN.py
tests/test_CKANData.py
tests/test_CKANTransform.py
tests/test_DataCache.py
tests/test_ckanCompare.py
tests/fixtures/CKANDataSet_fixtures.py
tests/fixtures/CKAN_fixtures.py
tests/fixtures/DataCache_fixtures.py
tests/fixtures/__init__.py
tests/fixtures/bcdc_fixtures.py
tests/fixtures/constants_fixtures.py
tests/fixtures/transformation_fixures.py
tests/helpers/CKANDataHelpers.py
tests/helpers/__init__.py
bcdc2bcdc-0.0.10.dist-info/LICENSE
bcdc2bcdc-0.0.10.dist-info/METADATA
bcdc2bcdc-0.0.10.dist-info/WHEEL
bcdc2bcdc-0.0.10.dist-info/top_level.txt
bcdc2bcdc-0.0.10.dist-info/RECORD
