Metadata-Version: 2.1
Name: bcdc2bcdc
Version: 0.0.10
Summary: Utility for moving data between CKAN instances using the API
Home-page: https://github.com/bcgov/bcdc2bcdc
Author: Kevin Netherton
Author-email: kevin.netherton@gov.bc.ca
License: UNKNOWN
Platform: UNKNOWN
Classifier: Development Status :: 4 - Beta
Classifier: Programming Language :: Python :: 3.6
Classifier: License :: OSI Approved :: Apache Software License
Classifier: Topic :: Software Development :: Testing
Classifier: Operating System :: OS Independent
Requires-Python: >=3.6.*, <4
Requires-Dist: ckanapi (==4.3)
Requires-Dist: deepdiff (==4.3.2)
Requires-Dist: json-delta (==2.0)
Requires-Dist: requests-futures (==1.0.0)
Requires-Dist: requests (==2.23.0)
